VirxERLU_RLib-1.2.0.dist-info/METADATA
VirxERLU_RLib-1.2.0.dist-info/WHEEL
virx_erlu_rlib/__init__.py
virx_erlu_rlib/__init__.pyi
virx_erlu_rlib/py.typed
virx_erlu_rlib/virx_erlu_rlib.pyd
VirxERLU_RLib-1.2.0.dist-info/RECORD
