Metadata-Version: 2.1
Name: VirxERLU-RLib
Version: 1.2.0
Classifier: License :: OSI Approved :: MIT License
Classifier: Intended Audience :: Developers
Classifier: Development Status :: 5 - Production/Stable
Classifier: Programming Language :: Python :: 3.7
Classifier: Programming Language :: Python :: 3.8
Classifier: Programming Language :: Python :: 3.9
Classifier: Programming Language :: Python :: 3.10
Classifier: Programming Language :: Python :: 3.11
Classifier: Operating System :: POSIX :: Linux
Classifier: Operating System :: Microsoft :: Windows
Summary: Rust modules for VirxERLU
Home-Page: https://github.com/VirxEC/VirxERLU-RLib
Author: VirxEC <virx@virxcase.dev>
Author-email: VirxEC <virx@virxcase.dev>
License: MIT
